pyams_http_proxy/__init__.py
pyams_http_proxy/proxy.py
pyams_http_proxy/webapp.py
pyams_http_proxy/doctests/README.rst
pyams_http_proxy/plugin/__init__.py
pyams_http_proxy/plugin/body_logger.py
pyams_http_proxy/plugin/es_logger.py
pyams_http_proxy/plugin/json_rewrite.py
pyams_http_proxy/plugin/monitor.py
pyams_http_proxy/plugin/request_headers.py
pyams_http_proxy/tests/__init__.py
pyams_http_proxy/tests/test_utilsdocs.py
pyams_http_proxy/tests/test_utilsdocstrings.py
pyams_http_proxy-1.7.1.dist-info/LICENSE
pyams_http_proxy-1.7.1.dist-info/METADATA
pyams_http_proxy-1.7.1.dist-info/WHEEL
pyams_http_proxy-1.7.1.dist-info/namespace_packages.txt
pyams_http_proxy-1.7.1.dist-info/top_level.txt
pyams_http_proxy-1.7.1.dist-info/RECORD
