Metadata-Version: 2.1
Name: pyams-http-proxy
Version: 1.7.1
Summary: PyAMS HTTP proxy
Home-page: https://pyams.readthedocs.io
Author: Thierry Florac
Author-email: tflorac@ulthar.net
License: ZPL
Keywords: Pyramid PyAMS
Classifier: License :: OSI Approved :: Zope Public License
Classifier: Development Status :: 4 - Beta
Classifier: Programming Language :: Python
Classifier: Framework :: Pyramid
Classifier: Topic :: Software Development :: Libraries :: Python Modules
License-File: LICENSE
Requires-Dist: setuptools
Requires-Dist: httpx
Requires-Dist: python-multipart
Requires-Dist: starlette
Provides-Extra: test
